LICENSE
MANIFEST.in
README.md
VERSION
pyproject.toml
requirements.txt
setup.py
covalent_kubernetes_plugin/__init__.py
covalent_kubernetes_plugin/k8s.py
covalent_kubernetes_plugin.egg-info/PKG-INFO
covalent_kubernetes_plugin.egg-info/SOURCES.txt
covalent_kubernetes_plugin.egg-info/dependency_links.txt
covalent_kubernetes_plugin.egg-info/entry_points.txt
covalent_kubernetes_plugin.egg-info/requires.txt
covalent_kubernetes_plugin.egg-info/top_level.txt